pylioness/__init__.py
pylioness/_metadata.py
pylioness/lioness.py
pylioness-0.0.1.dist-info/DESCRIPTION.rst
pylioness-0.0.1.dist-info/METADATA
pylioness-0.0.1.dist-info/RECORD
pylioness-0.0.1.dist-info/WHEEL
pylioness-0.0.1.dist-info/metadata.json
pylioness-0.0.1.dist-info/top_level.txt
