Metadata-Version: 2.0
Name: pylioness
Version: 0.0.1
Summary:     python lioness block cipher
Requires-Dist: pyblake2 (>=0.9.3)
Requires-Dist: pycrypto (>=2.6.1)
Requires-Dist: pycryptodomex (>=3.4.3)
